[
  {
    "loginName": "hesiwei"
  },
  {
    "loginName": "duanshuting"
  },
  {
    "loginName": "liqingqing"
  },
  {
    "loginName": "huhangkai"
  },
  {
    "loginName": "zhanghui"
  },
  {
    "loginName": "tangtian"
  },
  {
    "loginName": "xiaohuiwen"
  },
  {
    "loginName": "zhouxiao"
  },
  {
    "loginName": "zhangjian"
  },
  {
    "loginName": "daizhuye"
  },
  {
    "loginName": "liuzhongzhu"
  },
  {
    "loginName": "machengxun"
  },
  {
    "loginName": "chenghailin"
  },
  {
    "loginName": "pengwanru"
  },
  {
    "loginName": "zhanglu"
  },
  {
    "loginName": "lihuang"
  },
  {
    "loginName": "ouyangwenlu"
  },
  {
    "loginName": "zhoujingyi"
  },
  {
    "loginName": "chenshihan"
  },
  {
    "loginName": "gaoyiao"
  },
  {
    "loginName": "xiayuting"
  },
  {
    "loginName": "luanqi"
  },
  {
    "loginName": "liyuhang"
  },
  {
    "loginName": "huangxinfei"
  },
  {
    "loginName": "heshize"
  },
  {
    "loginName": "zhangxiangyi"
  },
  {
    "loginName": "tangfuxiong"
  },
  {
    "loginName": "caiyulin"
  },
  {
    "loginName": "zhangjingying"
  },
  {
    "loginName": "zhanghuiwen"
  },
  {
    "loginName": "fengzixia"
  },
  {
    "loginName": "jiangjiayu"
  },
  {
    "loginName": "yanghuanling"
  },
  {
    "loginName": "zhangzijian"
  },
  {
    "loginName": "zhuzixi"
  },
  {
    "loginName": "wangjiangjin"
  },
  {
    "loginName": "liuchengxin"
  },
  {
    "loginName": "liuqixiang"
  },
  {
    "loginName": "kuangxiaojie"
  },
  {
    "loginName": "huangjunjia"
  },
  {
    "loginName": "kuangbo"
  },
  {
    "loginName": "yinzihao"
  },
  {
    "loginName": "chensirong"
  },
  {
    "loginName": "yinruijie"
  },
  {
    "loginName": "jiangxinyi"
  },
  {
    "loginName": "dongyu"
  },
  {
    "loginName": "fangran"
  },
  {
    "loginName": "wujiajia"
  },
  {
    "loginName": "yuziyi"
  },
  {
    "loginName": "leitianqi"
  },
  {
    "loginName": "zhangmengling"
  },
  {
    "loginName": "xiezhiyu"
  },
  {
    "loginName": "gaoyuying"
  },
  {
    "loginName": "huangxiong"
  },
  {
    "loginName": "chenyongtai"
  },
  {
    "loginName": "wengjiaxin"
  },
  {
    "loginName": "xiaweikai"
  },
  {
    "loginName": "shijinwen"
  },
  {
    "loginName": "pengweihai"
  },
  {
    "loginName": "tanzexi"
  },
  {
    "loginName": "huangxiao"
  },
  {
    "loginName": "chenyanfei"
  },
  {
    "loginName": "wenjixiang"
  },
  {
    "loginName": "wenxueyao"
  },
  {
    "loginName": "chenlingyan"
  },
  {
    "loginName": "hanleyan"
  },
  {
    "loginName": "xianjinyao"
  },
  {
    "loginName": "dengxinjie"
  },
  {
    "loginName": "ouyangxiaoqing"
  },
  {
    "loginName": "liuxinni"
  },
  {
    "loginName": "zhangzirui"
  },
  {
    "loginName": "jianglinyou"
  },
  {
    "loginName": "wangliangyu"
  },
  {
    "loginName": "chengyihan"
  },
  {
    "loginName": "shibowen"
  },
  {
    "loginName": "fanfengku"
  },
  {
    "loginName": "yangzihan"
  },
  {
    "loginName": "wudi"
  },
  {
    "loginName": "ouyangmaolin"
  },
  {
    "loginName": "maozhaoxun"
  },
  {
    "loginName": "xiaokaiwen"
  },
  {
    "loginName": "xiaozihan"
  },
  {
    "loginName": "liyuzhang"
  },
  {
    "loginName": "wusuqi"
  },
  {
    "loginName": "yinpeng"
  },
  {
    "loginName": "cengyu"
  },
  {
    "loginName": "lijiaheng"
  },
  {
    "loginName": "lijiner"
  },
  {
    "loginName": "zhangchuxian"
  },
  {
    "loginName": "yeshaokun"
  },
  {
    "loginName": "tanyuanzhi"
  },
  {
    "loginName": "wuwenjie"
  },
  {
    "loginName": "heruizhi"
  },
  {
    "loginName": "xiaojian"
  },
  {
    "loginName": "gongshangyu"
  },
  {
    "loginName": "fanyimin"
  },
  {
    "loginName": "wangyiaoxue"
  },
  {
    "loginName": "yangjingxiang"
  },
  {
    "loginName": "renjiayi"
  },
  {
    "loginName": "lichaofan"
  },
  {
    "loginName": "qiyirong"
  },
  {
    "loginName": "liujiayu"
  },
  {
    "loginName": "chenbochen"
  },
  {
    "loginName": "lu:wanying"
  },
  {
    "loginName": "pengrenxi"
  },
  {
    "loginName": "ningjinyu"
  },
  {
    "loginName": "zhouchaoxian"
  },
  {
    "loginName": "yangsuxin"
  },
  {
    "loginName": "weijingwen"
  },
  {
    "loginName": "lishuhan"
  },
  {
    "loginName": "yanzhiheng"
  },
  {
    "loginName": "chenzehan"
  },
  {
    "loginName": "zhuruyi"
  },
  {
    "loginName": "tanghaowei"
  },
  {
    "loginName": "wujun"
  },
  {
    "loginName": "lijiaxing"
  },
  {
    "loginName": "duanzixiong"
  },
  {
    "loginName": "lanxinlin"
  },
  {
    "loginName": "hezhehan"
  },
  {
    "loginName": "wuchuangxin"
  },
  {
    "loginName": "cengyuqian"
  },
  {
    "loginName": "zhouzihan"
  },
  {
    "loginName": "limengzhi"
  },
  {
    "loginName": "xiaokaiyang"
  },
  {
    "loginName": "lijiarun"
  },
  {
    "loginName": "liusitong"
  },
  {
    "loginName": "zhaoyihan"
  },
  {
    "loginName": "longtongbo"
  },
  {
    "loginName": "liangbowen"
  },
  {
    "loginName": "liuwenda"
  },
  {
    "loginName": "tangyanping"
  },
  {
    "loginName": "zhongbingheng"
  },
  {
    "loginName": "zhouzichuan"
  },
  {
    "loginName": "tangsiyi"
  },
  {
    "loginName": "tangwenqi"
  },
  {
    "loginName": "xiaobiyuan"
  },
  {
    "loginName": "yangwenhua"
  },
  {
    "loginName": "xiangjunyu"
  },
  {
    "loginName": "tongke"
  },
  {
    "loginName": "liujirui"
  },
  {
    "loginName": "lihaoxuan"
  },
  {
    "loginName": "quedingyu"
  },
  {
    "loginName": "chenhang"
  },
  {
    "loginName": "guziyao"
  },
  {
    "loginName": "pengrunkun"
  },
  {
    "loginName": "wujianghong"
  },
  {
    "loginName": "liujie"
  },
  {
    "loginName": "liupengju"
  },
  {
    "loginName": "yinmohan"
  },
  {
    "loginName": "yeyuxuan"
  },
  {
    "loginName": "xiaohongwu"
  },
  {
    "loginName": "houxinying"
  },
  {
    "loginName": "liuxi"
  },
  {
    "loginName": "liujiazhen"
  },
  {
    "loginName": "ouyangqunmin"
  },
  {
    "loginName": "yuanmengci"
  },
  {
    "loginName": "zhaobo"
  },
  {
    "loginName": "liuxinyi"
  },
  {
    "loginName": "wangjing"
  },
  {
    "loginName": "zhaoziquan"
  },
  {
    "loginName": "chenyi"
  },
  {
    "loginName": "fanzimo"
  },
  {
    "loginName": "wuaofeng"
  },
  {
    "loginName": "zhangyulu"
  },
  {
    "loginName": "luxinyan"
  },
  {
    "loginName": "fanxucong"
  },
  {
    "loginName": "yanzihan"
  },
  {
    "loginName": "yanshuairong"
  },
  {
    "loginName": "zhangxiang"
  },
  {
    "loginName": "hexuan"
  },
  {
    "loginName": "wangwentao"
  },
  {
    "loginName": "chengpeng"
  },
  {
    "loginName": "liyuxuan"
  },
  {
    "loginName": "jiangchong"
  },
  {
    "loginName": "fuqianying"
  },
  {
    "loginName": "manting"
  },
  {
    "loginName": "zoujiayi"
  },
  {
    "loginName": "cengzhanpeng"
  },
  {
    "loginName": "bianjiashi"
  },
  {
    "loginName": "zouzonghan"
  },
  {
    "loginName": "xiangtang"
  },
  {
    "loginName": "zhengqi"
  },
  {
    "loginName": "yuanyiyi"
  },
  {
    "loginName": "libaoqing"
  },
  {
    "loginName": "shujiaming"
  },
  {
    "loginName": "yangqian"
  },
  {
    "loginName": "xiaokaiyan"
  },
  {
    "loginName": "limengzi"
  },
  {
    "loginName": "liujiahao"
  },
  {
    "loginName": "chenyishan"
  },
  {
    "loginName": "huhongji"
  },
  {
    "loginName": "yangxiaochao"
  },
  {
    "loginName": "yangzhuoren"
  },
  {
    "loginName": "wangyanheng"
  },
  {
    "loginName": "luqianhe"
  },
  {
    "loginName": "chengyan"
  },
  {
    "loginName": "shencengxin"
  },
  {
    "loginName": "moyangqian"
  },
  {
    "loginName": "lijing"
  },
  {
    "loginName": "chenjiayi"
  },
  {
    "loginName": "cengzhenyu"
  },
  {
    "loginName": "luozewu"
  },
  {
    "loginName": "lu:jiasai"
  },
  {
    "loginName": "huangxin"
  },
  {
    "loginName": "zhengyuanqi"
  },
  {
    "loginName": "xuejiaqi"
  },
  {
    "loginName": "xiangning"
  },
  {
    "loginName": "zhanghaoneng"
  },
  {
    "loginName": "chenqibin"
  },
  {
    "loginName": "cengjie"
  },
  {
    "loginName": "mihaoran"
  },
  {
    "loginName": "zhangzhen"
  },
  {
    "loginName": "lichunyong"
  },
  {
    "loginName": "liuyaosheng"
  },
  {
    "loginName": "zhouzixin"
  },
  {
    "loginName": "liruobin"
  },
  {
    "loginName": "yangjiayi"
  },
  {
    "loginName": "zhongjuan"
  },
  {
    "loginName": "yangmanni"
  },
  {
    "loginName": "cengkunshan"
  },
  {
    "loginName": "liukecheng"
  },
  {
    "loginName": "luyicheng"
  },
  {
    "loginName": "zhangwenjie"
  },
  {
    "loginName": "zhouxiulin"
  },
  {
    "loginName": "zhangwenqing"
  },
  {
    "loginName": "mayaqi"
  },
  {
    "loginName": "gaoyue"
  },
  {
    "loginName": "zhushiya"
  },
  {
    "loginName": "hezixuan"
  },
  {
    "loginName": "hejiayan"
  },
  {
    "loginName": "wangyingnan"
  },
  {
    "loginName": "xiongshuai"
  },
  {
    "loginName": "hongyeqin"
  },
  {
    "loginName": "zouyuke"
  },
  {
    "loginName": "gongbo"
  },
  {
    "loginName": "liuyangshuai"
  },
  {
    "loginName": "zhouxiangcheng"
  },
  {
    "loginName": "liwending"
  },
  {
    "loginName": "hexinhui"
  },
  {
    "loginName": "liangbowen"
  },
  {
    "loginName": "hexinyue"
  },
  {
    "loginName": "zhouhan"
  },
  {
    "loginName": "wuyunlong"
  },
  {
    "loginName": "liuzirui"
  },
  {
    "loginName": "zhaojiayu"
  },
  {
    "loginName": "pengxinyu"
  },
  {
    "loginName": "tongsijin"
  },
  {
    "loginName": "shichongrui"
  },
  {
    "loginName": "wangyuqian"
  },
  {
    "loginName": "xiaoshuai"
  },
  {
    "loginName": "guanyukun"
  },
  {
    "loginName": "sunbaoyangyang"
  },
  {
    "loginName": "xiaobang"
  },
  {
    "loginName": "zhuli"
  },
  {
    "loginName": "yangyi"
  },
  {
    "loginName": "dengwencan"
  },
  {
    "loginName": "yubohao"
  },
  {
    "loginName": "gaoyiming"
  },
  {
    "loginName": "zhanglinbo"
  },
  {
    "loginName": "liyuan"
  },
  {
    "loginName": "zhangwangjun"
  },
  {
    "loginName": "liushihao"
  },
  {
    "loginName": "wangyuhai"
  },
  {
    "loginName": "tanjiahao"
  },
  {
    "loginName": "xudan"
  },
  {
    "loginName": "zhuminglei"
  },
  {
    "loginName": "caoyixuan"
  },
  {
    "loginName": "pengjiaying"
  },
  {
    "loginName": "chenjingyi"
  },
  {
    "loginName": "lizhuolin"
  },
  {
    "loginName": "guozhuiwen"
  },
  {
    "loginName": "kuangziyu"
  },
  {
    "loginName": "xiangjunyi"
  },
  {
    "loginName": "liuyixuan"
  },
  {
    "loginName": "zhangruitao"
  },
  {
    "loginName": "dengmingtao"
  },
  {
    "loginName": "zhangzeya"
  },
  {
    "loginName": "wuyizhen"
  },
  {
    "loginName": "yangzhangtao"
  },
  {
    "loginName": "liushengzheng"
  },
  {
    "loginName": "caotianqi"
  },
  {
    "loginName": "panchaomuzi"
  },
  {
    "loginName": "zhangjiaxun"
  },
  {
    "loginName": "yangyi"
  },
  {
    "loginName": "ouyangyu"
  },
  {
    "loginName": "tangzhenyao"
  },
  {
    "loginName": "luozhuoyang"
  },
  {
    "loginName": "yintingyu"
  },
  {
    "loginName": "wuwenxing"
  },
  {
    "loginName": "lijianwei"
  },
  {
    "loginName": "leiyu"
  },
  {
    "loginName": "panying"
  },
  {
    "loginName": "dengzicai"
  },
  {
    "loginName": "tangruoqian"
  },
  {
    "loginName": "lilun"
  },
  {
    "loginName": "panyi"
  },
  {
    "loginName": "chenjiaxin"
  },
  {
    "loginName": "yangziyue"
  },
  {
    "loginName": "zhuyizhen"
  },
  {
    "loginName": "huhengkai"
  },
  {
    "loginName": "wangxuan"
  },
  {
    "loginName": "wangyi"
  },
  {
    "loginName": "yanyuyang"
  },
  {
    "loginName": "xuyangku"
  },
  {
    "loginName": "yuhuanwen"
  },
  {
    "loginName": "zhangbolin"
  },
  {
    "loginName": "chutong"
  },
  {
    "loginName": "hejunxiang"
  },
  {
    "loginName": "luoxiangyuan"
  },
  {
    "loginName": "ningyi"
  },
  {
    "loginName": "tanghuiyi"
  },
  {
    "loginName": "zhusiyu"
  },
  {
    "loginName": "fanhaoyue"
  },
  {
    "loginName": "zhoujingru"
  },
  {
    "loginName": "wangyanbin"
  },
  {
    "loginName": "ouyanglujia"
  },
  {
    "loginName": "zhouquan"
  },
  {
    "loginName": "yangjiajun"
  },
  {
    "loginName": "wanghaoyu"
  },
  {
    "loginName": "hejianlian"
  },
  {
    "loginName": "wangjunhan"
  },
  {
    "loginName": "tanshangwei"
  },
  {
    "loginName": "cengruixi"
  },
  {
    "loginName": "lizini"
  },
  {
    "loginName": "xiaokaiyuan"
  },
  {
    "loginName": "xurenhao"
  },
  {
    "loginName": "xiezhixu"
  },
  {
    "loginName": "zhaodongcheng"
  },
  {
    "loginName": "huangyu"
  },
  {
    "loginName": "mojiahao"
  },
  {
    "loginName": "liuganlu"
  },
  {
    "loginName": "yizeyuan"
  },
  {
    "loginName": "nihaoran"
  },
  {
    "loginName": "wuzhuoyan"
  },
  {
    "loginName": "tanjie"
  },
  {
    "loginName": "zhouliyang"
  },
  {
    "loginName": "liuzijiang"
  },
  {
    "loginName": "zhuxuanyou"
  },
  {
    "loginName": "xuduo"
  },
  {
    "loginName": "yangyuxi"
  },
  {
    "loginName": "qiushuyu"
  },
  {
    "loginName": "fengtao"
  },
  {
    "loginName": "yangyu"
  },
  {
    "loginName": "hushimeng"
  },
  {
    "loginName": "huangwen"
  },
  {
    "loginName": "liujianlin"
  },
  {
    "loginName": "wuyajie"
  },
  {
    "loginName": "qiulingrui"
  },
  {
    "loginName": "wuxianwen"
  },
  {
    "loginName": "zhaoyang"
  },
  {
    "loginName": "liushixiong"
  },
  {
    "loginName": "songyiheng"
  },
  {
    "loginName": "yaochun"
  },
  {
    "loginName": "weiqianyu"
  },
  {
    "loginName": "wangyuling"
  },
  {
    "loginName": "liuning"
  },
  {
    "loginName": "liutianye"
  },
  {
    "loginName": "yizijun"
  },
  {
    "loginName": "xiongyujia"
  },
  {
    "loginName": "zhouzhihao"
  },
  {
    "loginName": "zhangchuyang"
  },
  {
    "loginName": "ganyiyang"
  },
  {
    "loginName": "gaoleyao"
  },
  {
    "loginName": "wanghuilan"
  },
  {
    "loginName": "daijingyu"
  },
  {
    "loginName": "liuhanyang"
  },
  {
    "loginName": "sunchaoyan"
  },
  {
    "loginName": "shaochongjun"
  },
  {
    "loginName": "wangjunsong"
  },
  {
    "loginName": "chenjiahui"
  },
  {
    "loginName": "caojinxuan"
  },
  {
    "loginName": "dingziling"
  },
  {
    "loginName": "fengshiqi"
  },
  {
    "loginName": "tangyekang"
  },
  {
    "loginName": "liyiyang"
  },
  {
    "loginName": "pengyanqiao"
  },
  {
    "loginName": "pilangyi"
  },
  {
    "loginName": "tongxiaoya"
  },
  {
    "loginName": "xiaguihao"
  },
  {
    "loginName": "jiangzhengjie"
  },
  {
    "loginName": "tanjianing"
  },
  {
    "loginName": "lizhanghan"
  },
  {
    "loginName": "zhouxiangyu"
  },
  {
    "loginName": "xuyao"
  },
  {
    "loginName": "longzikuang"
  },
  {
    "loginName": "huangziying"
  },
  {
    "loginName": "tanhaowen"
  },
  {
    "loginName": "hujiayu"
  }
]